ytm_ll_dl/__init__.py
ytm_ll_dl/bash.py
ytm_ll_dl/index_helpers.py
ytm_ll_dl/main.py
ytm_ll_dl/slugify.py
ytm_ll_dl-0.1.0.dist-info/entry_points.txt
ytm_ll_dl-0.1.0.dist-info/WHEEL
ytm_ll_dl-0.1.0.dist-info/METADATA
ytm_ll_dl-0.1.0.dist-info/RECORD
