Metadata-Version: 2.1
Name: ytm-ll-dl
Version: 0.1.0
Summary: Download 'Liked music' playlist from Youtube Music
Author: kotborealis
Author-email: kotborealis@awooo.ru
Requires-Python: >=3.8,<4.0
Classifier: Programming Language :: Python :: 3
Classifier: Programming Language :: Python :: 3.8
Classifier: Programming Language :: Python :: 3.9
Classifier: Programming Language :: Python :: 3.10
Requires-Dist: click (>=8.1.3,<9.0.0)
Requires-Dist: sh (>=1.14.3,<2.0.0)
Requires-Dist: yt-dlp (>=2022.9.1,<2023.0.0)
Requires-Dist: ytmusicapi (>=0.22.0,<0.23.0)
